odoo/addons/stock_request_tier_validation/README.rst
odoo/addons/stock_request_tier_validation/__init__.py
odoo/addons/stock_request_tier_validation/__manifest__.py
odoo/addons/stock_request_tier_validation/data/stock_request_tier_definition.xml
odoo/addons/stock_request_tier_validation/i18n/es.po
odoo/addons/stock_request_tier_validation/i18n/pt_BR.po
odoo/addons/stock_request_tier_validation/i18n/stock_request_tier_validation.pot
odoo/addons/stock_request_tier_validation/i18n/zh_CN.po
odoo/addons/stock_request_tier_validation/models/__init__.py
odoo/addons/stock_request_tier_validation/models/stock_request.py
odoo/addons/stock_request_tier_validation/models/stock_request_order.py
odoo/addons/stock_request_tier_validation/models/tier_definition.py
odoo/addons/stock_request_tier_validation/readme/CONFIGURE.rst
odoo/addons/stock_request_tier_validation/readme/CONTRIBUTORS.rst
odoo/addons/stock_request_tier_validation/readme/CREDITS.rst
odoo/addons/stock_request_tier_validation/readme/DESCRIPTION.rst
odoo/addons/stock_request_tier_validation/readme/INSTALL.rst
odoo/addons/stock_request_tier_validation/readme/USAGE.rst
odoo/addons/stock_request_tier_validation/static/description/icon.png
odoo/addons/stock_request_tier_validation/static/description/index.html
odoo/addons/stock_request_tier_validation/tests/__init__.py
odoo/addons/stock_request_tier_validation/tests/test_stock_request_tier_validation.py
odoo/addons/stock_request_tier_validation/views/stock_request_order_view.xml
odoo/addons/stock_request_tier_validation/views/stock_request_view.xml
odoo12_addon_stock_request_tier_validation-12.0.1.2.1.dist-info/METADATA
odoo12_addon_stock_request_tier_validation-12.0.1.2.1.dist-info/WHEEL
odoo12_addon_stock_request_tier_validation-12.0.1.2.1.dist-info/top_level.txt
odoo12_addon_stock_request_tier_validation-12.0.1.2.1.dist-info/RECORD
